auto_feat_select_rupakbob/__init__.py
auto_feat_select_rupakbob/auto_feat_selection.py
auto_feat_selection-0.0.8.dist-info/LICENSE
auto_feat_selection-0.0.8.dist-info/METADATA
auto_feat_selection-0.0.8.dist-info/WHEEL
auto_feat_selection-0.0.8.dist-info/top_level.txt
auto_feat_selection-0.0.8.dist-info/RECORD
